.gitignore
COPYING.LESSER.txt
README.rst
setup.py
score/__init__.py
score.deploy.egg-info/PKG-INFO
score.deploy.egg-info/SOURCES.txt
score.deploy.egg-info/dependency_links.txt
score.deploy.egg-info/entry_points.txt
score.deploy.egg-info/namespace_packages.txt
score.deploy.egg-info/not-zip-safe
score.deploy.egg-info/requires.txt
score.deploy.egg-info/top_level.txt
score/deploy/__init__.py
score/deploy/_app.py
score/deploy/_init.py
score/deploy/cli.py